kobble_admin/__init__.py
kobble_admin/api.py
kobble_admin/gateway.py
kobble_admin/kobble.py
kobble_admin/products.py
kobble_admin/quotas.py
kobble_admin/users.py
kobble_admin/webhooks.py
kobble_admin-1.3.0.dist-info/METADATA
kobble_admin-1.3.0.dist-info/WHEEL
kobble_admin-1.3.0.dist-info/RECORD
