Metadata-Version: 2.1
Name: kobble-admin
Version: 1.3.0
Summary: Offical SDK to perform privileged operations on your Kobble app
Author: Aurelien Brabant
Author-email: aurelien@agentlabs.dev
Requires-Python: >=3.11,<4.0
Classifier: Programming Language :: Python :: 3
Classifier: Programming Language :: Python :: 3.11
Classifier: Programming Language :: Python :: 3.12
Requires-Dist: pyjwt[crypto] (>=2.8.0,<3.0.0)
Requires-Dist: requests (>=2.31.0,<3.0.0)
